pipedrive/__init__.py
pipedrive/activities.py
pipedrive/client.py
pipedrive/deals.py
pipedrive/exceptions.py
pipedrive/filters.py
pipedrive/items.py
pipedrive/leads.py
pipedrive/notes.py
pipedrive/organizations.py
pipedrive/persons.py
pipedrive/pipelines.py
pipedrive/products.py
pipedrive/recents.py
pipedrive/search.py
pipedrive/stages.py
pipedrive/subscriptions.py
pipedrive/teams.py
pipedrive/users.py
pipedrive/webhooks.py
api_pipedrive_python-1.3.dist-info/licenses/LICENSE
api_pipedrive_python-1.3.dist-info/METADATA
api_pipedrive_python-1.3.dist-info/WHEEL
api_pipedrive_python-1.3.dist-info/RECORD
