Metadata-Version: 2.4
Name: api-pipedrive-python
Version: 1.3
Summary: API wrapper for Pipedrive written in Python
License: MIT
License-File: LICENSE
Author: Weriqui Ferreira de Souza
Author-email: weriquetiao@gmail.com
Requires-Python: >=3.9,<4.0
Classifier: License :: OSI Approved :: MIT License
Classifier: Programming Language :: Python :: 3
Classifier: Programming Language :: Python :: 3.9
Classifier: Programming Language :: Python :: 3.10
Classifier: Programming Language :: Python :: 3.11
Classifier: Programming Language :: Python :: 3.12
Classifier: Programming Language :: Python :: 3.13
Classifier: Programming Language :: Python :: 3.14
